{
  "version": 1,
  "presets": [
    {
      "id": "gibson_les_paul",
      "name": "Gibson Les Paul",
      "units": "in",
      "geometry": {
        "scale_length": 24.75,
        "num_frets": 22,
        "num_strings": 6,
        "fingerboard_width_at_nut": 1.695,
        "fingerboard_width_at_12th_fret": 2.26,
        "fingerboard_radius": 12.0
      },
      "metadata": {
        "fingerboard_material": "Rosewood",
        "fret_material": "Nickel Silver",
        "nut_material": "Graph Tech",
        "inlay_material": "Acrylic",
        "inlay_style": "Trapezoid"
      }
    },
    {
      "id": "fender_stratocaster",
      "name": "Fender Stratocaster",
      "units": "in",
      "geometry": {
        "scale_length": 25.5,
        "num_frets": 22,
        "num_strings": 6,
        "fingerboard_width_at_nut": 1.685,
        "fingerboard_width_at_12th_fret": 2.165,
        "fingerboard_radius": 9.5
      },
      "metadata": {
        "fingerboard_material": "Maple",
        "fret_material": "Nickel Silver",
        "nut_material": "Synthetic Bone",
        "inlay_material": "Acrylic",
        "inlay_style": "Dot"
      }
    },
    {
      "id": "fender_telecaster",
      "name": "Fender Telecaster",
      "units": "in",
      "geometry": {
        "scale_length": 25.5,
        "num_frets": 22,
        "num_strings": 6,
        "fingerboard_width_at_nut": 1.65,
        "fingerboard_width_at_12th_fret": 2.2,
        "fingerboard_radius": 9.5
      },
      "metadata": {
        "fingerboard_material": "Maple",
        "fret_material": "Nickel Silver",
        "nut_material": "Synthetic Bone",
        "inlay_material": "Acrylic",
        "inlay_style": "Dot"
      }
    },
    {
      "id": "prs_custom_24",
      "name": "PRS Custom 24",
      "units": "in",
      "geometry": {
        "scale_length": 25.0,
        "num_frets": 24,
        "num_strings": 6,
        "fingerboard_width_at_nut": 1.65,
        "fingerboard_width_at_12th_fret": 2.245,
        "fingerboard_radius": 10.0
      },
      "metadata": {
        "fingerboard_material": "Rosewood",
        "fret_material": "Nickel Silver",
        "nut_material": "Graph Tech",
        "inlay_material": "Abalone",
        "inlay_style": "Birds"
      }
    },
    {
      "id": "ibanez_rg",
      "name": "Ibanez RG",
      "units": "in",
      "geometry": {
        "scale_length": 25.5,
        "num_frets": 24,
        "num_strings": 6,
        "fingerboard_width_at_nut": 1.692,
        "fingerboard_width_at_12th_fret": 2.283,
        "fingerboard_radius": 16.0
      },
      "metadata": {
        "fingerboard_material": "Rosewood",
        "fret_material": "Nickel Silver",
        "nut_material": "Graph Tech",
        "inlay_material": "Acrylic",
        "inlay_style": "Dot"
      }
    },
    {
      "id": "gibson_es_335",
      "name": "Gibson ES-335",
      "units": "in",
      "geometry": {
        "scale_length": 24.75,
        "num_frets": 22,
        "num_strings": 6,
        "fingerboard_width_at_nut": 1.6875,
        "fingerboard_width_at_12th_fret": 2.24,
        "fingerboard_radius": 12.0
      },
      "metadata": {
        "fingerboard_material": "Rosewood",
        "fret_material": "Nickel Silver",
        "nut_material": "Bone",
        "inlay_material": "Acrylic",
        "inlay_style": "Dot"
      }
    },
    {
      "id": "rickenbacker_360",
      "name": "Rickenbacker 360",
      "units": "in",
      "geometry": {
        "scale_length": 24.75,
        "num_frets": 24,
        "num_strings": 6,
        "fingerboard_width_at_nut": 1.63,
        "fingerboard_width_at_12th_fret": 1.93,
        "fingerboard_radius": 10.0
      },
      "metadata": {
        "fingerboard_material": "Rosewood",
        "fret_material": "Nickel Silver",
        "nut_material": "Bone",
        "inlay_material": "Acrylic",
        "inlay_style": "Triangle"
      }
    },
    {
      "id": "martin_d_28",
      "name": "Martin D-28",
      "units": "in",
      "geometry": {
        "scale_length": 25.4,
        "num_frets": 20,
        "num_strings": 6,
        "fingerboard_width_at_nut": 1.75,
        "fingerboard_width_at_12th_fret": 2.125,
        "fingerboard_radius": 16.0
      },
      "metadata": {
        "fingerboard_material": "Ebony",
        "fret_material": "Nickel Silver",
        "nut_material": "Bone",
        "inlay_material": "Mother of Pearl",
        "inlay_style": "Dot"
      }
    },
    {
      "id": "gretsch_white_falcon",
      "name": "Gretsch White Falcon",
      "units": "in",
      "geometry": {
        "scale_length": 25.5,
        "num_frets": 22,
        "num_strings": 6,
        "fingerboard_width_at_nut": 1.6875,
        "fingerboard_width_at_12th_fret": 2.218,
        "fingerboard_radius": 12.0
      },
      "metadata": {
        "fingerboard_material": "Ebony",
        "fret_material": "Nickel Silver",
        "nut_material": "Bone",
        "inlay_material": "Mother of Pearl",
        "inlay_style": "Neo-Classic Thumbnail"
      }
    },
    {
      "id": "taylor_814ce",
      "name": "Taylor 814ce",
      "units": "in",
      "geometry": {
        "scale_length": 25.5,
        "num_frets": 20,
        "num_strings": 6,
        "fingerboard_width_at_nut": 1.75,
        "fingerboard_width_at_12th_fret": 2.25,
        "fingerboard_radius": 15.0
      },
      "metadata": {
        "fingerboard_material": "Ebony",
        "fret_material": "Nickel Silver",
        "nut_material": "Tusq",
        "inlay_material": "Mother of Pearl",
        "inlay_style": "Element"
      }
    }
  ]
}
